{"10021211":{"text":"君は見た,はちみつを舐める,下半身裸の,黄色いくまの怪異を…！","imgUrl":"","floorName":"debug","author":"debug"},"10060601":{"text":"gold","imgUrl":"","floorName":"debug","author":"debug"},"13092722":{"text":"君は見た,はちみつを舐める,下半身裸の,黄色いくまの怪異を…！","imgUrl":"","floorName":"debug","author":"debug"},"18011314":{"text":"greeen,all greeeen","imgUrl":"","floorName":"debug","author":"debug"},"20231715":{"text":"新規登録にゃ","imgUrl":"","floorName":"debug","author":"debug"},"24191823":{"text":"redred","imgUrl":"","floorName":"debug","author":"debug"},"26192119":{"text":"pink","imgUrl":"","floorName":"debug","author":"debug"},"27081318":{"text":"debug","imgUrl":"","floorName":"debug","author":"debug"},"02020717":{"text":"君は見た,はちみつを舐める,下半身裸の,黄色いくまの怪異を…！","imgUrl":"","floorName":"debug","author":"debug"},"02282727":{"text":"卵焼き","imgUrl":"","floorName":"debug","author":"debug"},"07261501":{"text":"君は見た,はちみつを舐める,下半身裸の,黄色いくまの怪異を…！","imgUrl":"","floorName":"debug","author":"debug"},"08282111":{"text":"こんにちはこんにちは,こんにちは！","imgUrl":"","floorName":"debug","author":"debug"}}